ct_leg_bone_split_patch/__init__.py
ct_leg_bone_split_patch/blur.py
ct_leg_bone_split_patch/main.py
ct_leg_bone_split_patch/pth_list.py
ct_leg_bone_split_patch/unet.py
ct_leg_bone_split_patch-0.1.6.dist-info/LICENSE
ct_leg_bone_split_patch-0.1.6.dist-info/METADATA
ct_leg_bone_split_patch-0.1.6.dist-info/WHEEL
ct_leg_bone_split_patch-0.1.6.dist-info/RECORD
